MANIFEST.in
README.md
setup.py
bin/rhessys_calibrator.py
bin/rhessys_calibrator_behavioral.py
bin/rhessys_calibrator_postprocess.py
bin/rhessys_calibrator_postprocess_behavioral.py
bin/rhessys_calibrator_postprocess_behavioral_compare.py
bin/rhessys_calibrator_postprocess_behavioral_timeseries.py
bin/rhessys_calibrator_postprocess_export.py
bin/rhessys_calibrator_restart.py
bin/rhessys_calibrator_results.py
bin/rw2rc.py
bin/lsf-sim/bjobs.py
bin/lsf-sim/bsub.py
rhessyscalibrator/__init__.py
rhessyscalibrator/behavioral.py
rhessyscalibrator/calibration_parameters.py
rhessyscalibrator/calibration_runner.py
rhessyscalibrator/calibrator.py
rhessyscalibrator/model_runner_db.py
rhessyscalibrator/model_runner_db2.py
rhessyscalibrator/postprocess.py
rhessyscalibrator/postprocess_behavioral.py
rhessyscalibrator.egg-info/PKG-INFO
rhessyscalibrator.egg-info/SOURCES.txt
rhessyscalibrator.egg-info/dependency_links.txt
rhessyscalibrator.egg-info/not-zip-safe
rhessyscalibrator.egg-info/requires.txt
rhessyscalibrator.egg-info/top_level.txt
rhessyscalibrator/tests/__init__.py
rhessyscalibrator/tests/test_model_runner_db.py
rhessyscalibrator/tests/test_model_runner_db2.py
rhessyscalibrator/tests/test_rhessys_calibrator.py
rhessyscalibrator/tests/test_rhessys_calibrator_postprocess.py