Metadata-Version: 1.1
Name: rhessyscalibrator
Version: 2.1.0
Summary: Libraries and command-line scripts for handling RHESSys model calibration.
Home-page: https://github.com/selimnairb/RHESSysCalibrator
Author: Brian Miles
Author-email: brian_miles@unc.edu
License: BSD
Platform: UNKNOWN
Classifier: Development Status :: 5 - Production/Stable
Classifier: Environment :: Console
Classifier: Intended Audience :: Science/Research
Classifier: License :: OSI Approved :: BSD License
Classifier: Natural Language :: English
Classifier: Operating System :: Unix
Classifier: Topic :: Scientific/Engineering :: GIS
